first_zawakin_package/__init__.py
second_zawakin_package/__init__.py
first_zawakin_package-0.0.5.dist-info/METADATA
first_zawakin_package-0.0.5.dist-info/WHEEL
first_zawakin_package-0.0.5.dist-info/top_level.txt
first_zawakin_package-0.0.5.dist-info/zip-safe
first_zawakin_package-0.0.5.dist-info/RECORD
