Metadata-Version: 2.1
Name: first-zawakin-package
Version: 0.0.5
Summary: my description
Home-page: 
Author: zawakin
Author-email: zawawahoge@gmail.com
License: MIT
Keywords: zawakin
